{"nodes": [{"id": "home_pablo_coding_pergo_internal_api_handler_telegram_webhook_go", "label": "telegram_webhook.go", "file_type": "code", "source_file": "internal/api/handler/telegram_webhook.go", "source_location": "L1"}, {"id": "handler_telegramwebhookhandler", "label": "TelegramWebhookHandler", "file_type": "code", "source_file": "internal/api/handler/telegram_webhook.go", "source_location": "L26"}, {"id": "workspacerepository", "label": "WorkspaceRepository", "file_type": "code", "source_file": "", "source_location": "", "origin_file": "/home/pablo/Coding/PerGo/internal/api/handler/telegram_webhook.go"}, {"id": "credentialsrepository", "label": "CredentialsRepository", "file_type": "code", "source_file": "", "source_location": "", "origin_file": "/home/pablo/Coding/PerGo/internal/api/handler/telegram_webhook.go"}, {"id": "recipientsessionrepository", "label": "RecipientSessionRepository", "file_type": "code", "source_file": "", "source_location": "", "origin_file": "/home/pablo/Coding/PerGo/internal/api/handler/telegram_webhook.go"}, {"id": "inbounddeduprepository", "label": "InboundDedupRepository", "file_type": "code", "source_file": "", "source_location": "", "origin_file": "/home/pablo/Coding/PerGo/internal/api/handler/telegram_webhook.go"}, {"id": "s3client", "label": "S3Client", "file_type": "code", "source_file": "", "source_location": "", "origin_file": "/home/pablo/Coding/PerGo/internal/api/handler/telegram_webhook.go"}, {"id": "jetstreampublisher", "label": "JetStreamPublisher", "file_type": "code", "source_file": "", "source_location": "", "origin_file": "/home/pablo/Coding/PerGo/internal/api/handler/telegram_webhook.go"}, {"id": "writer", "label": "Writer", "file_type": "code", "source_file": "", "source_location": "", "origin_file": "/home/pablo/Coding/PerGo/internal/api/handler/telegram_webhook.go"}, {"id": "client", "label": "Client", "file_type": "code", "source_file": "", "source_location": "", "origin_file": "/home/pablo/Coding/PerGo/internal/api/handler/telegram_webhook.go"}, {"id": "home_pablo_coding_pergo_internal_api_handler_telegram_webhook_newtelegramwebhookhandler", "label": "NewTelegramWebhookHandler()", "file_type": "code", "source_file": "internal/api/handler/telegram_webhook.go", "source_location": "L39"}, {"id": "handler_telegramwebhookhandler_setbaseurl", "label": ".SetBaseURL()", "file_type": "code", "source_file": "internal/api/handler/telegram_webhook.go", "source_location": "L62"}, {"id": "handler_telegramupdate", "label": "telegramUpdate", "file_type": "code", "source_file": "internal/api/handler/telegram_webhook.go", "source_location": "L66"}, {"id": "telegrammessage", "label": "telegramMessage", "file_type": "code", "source_file": "", "source_location": "", "origin_file": "/home/pablo/Coding/PerGo/internal/api/handler/telegram_webhook.go"}, {"id": "handler_telegrammessage", "label": "telegramMessage", "file_type": "code", "source_file": "internal/api/handler/telegram_webhook.go", "source_location": "L71"}, {"id": "telegramchat", "label": "telegramChat", "file_type": "code", "source_file": "", "source_location": "", "origin_file": "/home/pablo/Coding/PerGo/internal/api/handler/telegram_webhook.go"}, {"id": "telegramphoto", "label": "telegramPhoto", "file_type": "code", "source_file": "", "source_location": "", "origin_file": "/home/pablo/Coding/PerGo/internal/api/handler/telegram_webhook.go"}, {"id": "telegramdocument", "label": "telegramDocument", "file_type": "code", "source_file": "", "source_location": "", "origin_file": "/home/pablo/Coding/PerGo/internal/api/handler/telegram_webhook.go"}, {"id": "telegramaudio", "label": "telegramAudio", "file_type": "code", "source_file": "", "source_location": "", "origin_file": "/home/pablo/Coding/PerGo/internal/api/handler/telegram_webhook.go"}, {"id": "telegramvideo", "label": "telegramVideo", "file_type": "code", "source_file": "", "source_location": "", "origin_file": "/home/pablo/Coding/PerGo/internal/api/handler/telegram_webhook.go"}, {"id": "telegramlocation", "label": "telegramLocation", "file_type": "code", "source_file": "", "source_location": "", "origin_file": "/home/pablo/Coding/PerGo/internal/api/handler/telegram_webhook.go"}, {"id": "telegramcontact", "label": "telegramContact", "file_type": "code", "source_file": "", "source_location": "", "origin_file": "/home/pablo/Coding/PerGo/internal/api/handler/telegram_webhook.go"}, {"id": "handler_telegramphoto", "label": "telegramPhoto", "file_type": "code", "source_file": "internal/api/handler/telegram_webhook.go", "source_location": "L84"}, {"id": "handler_telegramdocument", "label": "telegramDocument", "file_type": "code", "source_file": "internal/api/handler/telegram_webhook.go", "source_location": "L89"}, {"id": "handler_telegramaudio", "label": "telegramAudio", "file_type": "code", "source_file": "internal/api/handler/telegram_webhook.go", "source_location": "L95"}, {"id": "handler_telegramvideo", "label": "telegramVideo", "file_type": "code", "source_file": "internal/api/handler/telegram_webhook.go", "source_location": "L100"}, {"id": "handler_telegramlocation", "label": "telegramLocation", "file_type": "code", "source_file": "internal/api/handler/telegram_webhook.go", "source_location": "L105"}, {"id": "handler_telegramcontact", "label": "telegramContact", "file_type": "code", "source_file": "internal/api/handler/telegram_webhook.go", "source_location": "L110"}, {"id": "handler_telegramchat", "label": "telegramChat", "file_type": "code", "source_file": "internal/api/handler/telegram_webhook.go", "source_location": "L116"}, {"id": "handler_telegramconfig", "label": "telegramConfig", "file_type": "code", "source_file": "internal/api/handler/telegram_webhook.go", "source_location": "L120"}, {"id": "handler_telegramwebhookhandler_handle", "label": ".Handle()", "file_type": "code", "source_file": "internal/api/handler/telegram_webhook.go", "source_location": "L126"}, {"id": "context", "label": "Context", "file_type": "code", "source_file": "", "source_location": "", "origin_file": "/home/pablo/Coding/PerGo/internal/api/handler/telegram_webhook.go"}, {"id": "handler_telegramwebhookhandler_downloadtelegramfile", "label": ".downloadTelegramFile()", "file_type": "code", "source_file": "internal/api/handler/telegram_webhook.go", "source_location": "L305"}, {"id": "home_pablo_coding_pergo_internal_api_handler_telegram_webhook_sha256hash", "label": "sha256Hash()", "file_type": "code", "source_file": "internal/api/handler/telegram_webhook.go", "source_location": "L364"}], "edges": [{"source": "home_pablo_coding_pergo_internal_api_handler_telegram_webhook_go", "target": "go_pkg_context", "relation": "imports_from", "confidence": "EXTRACTED", "source_file": "internal/api/handler/telegram_webhook.go", "source_location": "L4", "weight": 1.0, "context": "import"}, {"source": "home_pablo_coding_pergo_internal_api_handler_telegram_webhook_go", "target": "go_pkg_crypto_sha256", "relation": "imports_from", "confidence": "EXTRACTED", "source_file": "internal/api/handler/telegram_webhook.go", "source_location": "L5", "weight": 1.0, "context": "import"}, {"source": "home_pablo_coding_pergo_internal_api_handler_telegram_webhook_go", "target": "go_pkg_encoding_hex", "relation": "imports_from", "confidence": "EXTRACTED", "source_file": "internal/api/handler/telegram_webhook.go", "source_location": "L6", "weight": 1.0, "context": "import"}, {"source": "home_pablo_coding_pergo_internal_api_handler_telegram_webhook_go", "target": "go_pkg_encoding_json", "relation": "imports_from", "confidence": "EXTRACTED", "source_file": "internal/api/handler/telegram_webhook.go", "source_location": "L7", "weight": 1.0, "context": "import"}, {"source": "home_pablo_coding_pergo_internal_api_handler_telegram_webhook_go", "target": "go_pkg_errors", "relation": "imports_from", "confidence": "EXTRACTED", "source_file": "internal/api/handler/telegram_webhook.go", "source_location": "L8", "weight": 1.0, "context": "import"}, {"source": "home_pablo_coding_pergo_internal_api_handler_telegram_webhook_go", "target": "go_pkg_fmt", "relation": "imports_from", "confidence": "EXTRACTED", "source_file": "internal/api/handler/telegram_webhook.go", "source_location": "L9", "weight": 1.0, "context": "import"}, {"source": "home_pablo_coding_pergo_internal_api_handler_telegram_webhook_go", "target": "go_pkg_io", "relation": "imports_from", "confidence": "EXTRACTED", "source_file": "internal/api/handler/telegram_webhook.go", "source_location": "L10", "weight": 1.0, "context": "import"}, {"source": "home_pablo_coding_pergo_internal_api_handler_telegram_webhook_go", "target": "go_pkg_log_slog", "relation": "imports_from", "confidence": "EXTRACTED", "source_file": "internal/api/handler/telegram_webhook.go", "source_location": "L11", "weight": 1.0, "context": "import"}, {"source": "home_pablo_coding_pergo_internal_api_handler_telegram_webhook_go", "target": "go_pkg_net_http", "relation": "imports_from", "confidence": "EXTRACTED", "source_file": "internal/api/handler/telegram_webhook.go", "source_location": "L12", "weight": 1.0, "context": "import"}, {"source": "home_pablo_coding_pergo_internal_api_handler_telegram_webhook_go", "target": "go_pkg_strconv", "relation": "imports_from", "confidence": "EXTRACTED", "source_file": "internal/api/handler/telegram_webhook.go", "source_location": "L13", "weight": 1.0, "context": "import"}, {"source": "home_pablo_coding_pergo_internal_api_handler_telegram_webhook_go", "target": "go_pkg_strings", "relation": "imports_from", "confidence": "EXTRACTED", "source_file": "internal/api/handler/telegram_webhook.go", "source_location": "L14", "weight": 1.0, "context": "import"}, {"source": "home_pablo_coding_pergo_internal_api_handler_telegram_webhook_go", "target": "go_pkg_time", "relation": "imports_from", "confidence": "EXTRACTED", "source_file": "internal/api/handler/telegram_webhook.go", "source_location": "L15", "weight": 1.0, "context": "import"}, {"source": "home_pablo_coding_pergo_internal_api_handler_telegram_webhook_go", "target": "go_pkg_github_com_google_uuid", "relation": "imports_from", "confidence": "EXTRACTED", "source_file": "internal/api/handler/telegram_webhook.go", "source_location": "L17", "weight": 1.0, "context": "import"}, {"source": "home_pablo_coding_pergo_internal_api_handler_telegram_webhook_go", "target": "go_pkg_github_com_labstack_echo_v5", "relation": "imports_from", "confidence": "EXTRACTED", "source_file": "internal/api/handler/telegram_webhook.go", "source_location": "L18", "weight": 1.0, "context": "import"}, {"source": "home_pablo_coding_pergo_internal_api_handler_telegram_webhook_go", "target": "go_pkg_github_com_pablojhp_pergo_internal_platform_audit", "relation": "imports_from", "confidence": "EXTRACTED", "source_file": "internal/api/handler/telegram_webhook.go", "source_location": "L19", "weight": 1.0, "context": "import"}, {"source": "home_pablo_coding_pergo_internal_api_handler_telegram_webhook_go", "target": "go_pkg_github_com_pablojhp_pergo_internal_platform_queue", "relation": "imports_from", "confidence": "EXTRACTED", "source_file": "internal/api/handler/telegram_webhook.go", "source_location": "L20", "weight": 1.0, "context": "import"}, {"source": "home_pablo_coding_pergo_internal_api_handler_telegram_webhook_go", "target": "go_pkg_github_com_pablojhp_pergo_internal_platform_storage", "relation": "imports_from", "confidence": "EXTRACTED", "source_file": "internal/api/handler/telegram_webhook.go", "source_location": "L21", "weight": 1.0, "context": "import"}, {"source": "home_pablo_coding_pergo_internal_api_handler_telegram_webhook_go", "target": "go_pkg_github_com_pablojhp_pergo_internal_repository", "relation": "imports_from", "confidence": "EXTRACTED", "source_file": "internal/api/handler/telegram_webhook.go", "source_location": "L22", "weight": 1.0, "context": "import"}, {"source": "home_pablo_coding_pergo_internal_api_handler_telegram_webhook_go", "target": "handler_telegramwebhookhandler", "relation": "contains", "confidence": "EXTRACTED", "source_file": "internal/api/handler/telegram_webhook.go", "source_location": "L26", "weight": 1.0}, {"source": "handler_telegramwebhookhandler", "target": "workspacerepository", "relation": "references", "confidence": "EXTRACTED", "source_file": "internal/api/handler/telegram_webhook.go", "source_location": "L27", "weight": 1.0, "context": "field"}, {"source": "handler_telegramwebhookhandler", "target": "credentialsrepository", "relation": "references", "confidence": "EXTRACTED", "source_file": "internal/api/handler/telegram_webhook.go", "source_location": "L28", "weight": 1.0, "context": "field"}, {"source": "handler_telegramwebhookhandler", "target": "recipientsessionrepository", "relation": "references", "confidence": "EXTRACTED", "source_file": "internal/api/handler/telegram_webhook.go", "source_location": "L29", "weight": 1.0, "context": "field"}, {"source": "handler_telegramwebhookhandler", "target": "inbounddeduprepository", "relation": "references", "confidence": "EXTRACTED", "source_file": "internal/api/handler/telegram_webhook.go", "source_location": "L30", "weight": 1.0, "context": "field"}, {"source": "handler_telegramwebhookhandler", "target": "s3client", "relation": "references", "confidence": "EXTRACTED", "source_file": "internal/api/handler/telegram_webhook.go", "source_location": "L31", "weight": 1.0, "context": "field"}, {"source": "handler_telegramwebhookhandler", "target": "jetstreampublisher", "relation": "references", "confidence": "EXTRACTED", "source_file": "internal/api/handler/telegram_webhook.go", "source_location": "L32", "weight": 1.0, "context": "field"}, {"source": "handler_telegramwebhookhandler", "target": "writer", "relation": "references", "confidence": "EXTRACTED", "source_file": "internal/api/handler/telegram_webhook.go", "source_location": "L33", "weight": 1.0, "context": "field"}, {"source": "handler_telegramwebhookhandler", "target": "client", "relation": "references", "confidence": "EXTRACTED", "source_file": "internal/api/handler/telegram_webhook.go", "source_location": "L34", "weight": 1.0, "context": "field"}, {"source": "home_pablo_coding_pergo_internal_api_handler_telegram_webhook_go", "target": "home_pablo_coding_pergo_internal_api_handler_telegram_webhook_newtelegramwebhookhandler", "relation": "contains", "confidence": "EXTRACTED", "source_file": "internal/api/handler/telegram_webhook.go", "source_location": "L39", "weight": 1.0}, {"source": "home_pablo_coding_pergo_internal_api_handler_telegram_webhook_newtelegramwebhookhandler", "target": "workspacerepository", "relation": "references", "confidence": "EXTRACTED", "source_file": "internal/api/handler/telegram_webhook.go", "source_location": "L39", "weight": 1.0, "context": "parameter_type"}, {"source": "home_pablo_coding_pergo_internal_api_handler_telegram_webhook_newtelegramwebhookhandler", "target": "credentialsrepository", "relation": "references", "confidence": "EXTRACTED", "source_file": "internal/api/handler/telegram_webhook.go", "source_location": "L39", "weight": 1.0, "context": "parameter_type"}, {"source": "home_pablo_coding_pergo_internal_api_handler_telegram_webhook_newtelegramwebhookhandler", "target": "recipientsessionrepository", "relation": "references", "confidence": "EXTRACTED", "source_file": "internal/api/handler/telegram_webhook.go", "source_location": "L39", "weight": 1.0, "context": "parameter_type"}, {"source": "home_pablo_coding_pergo_internal_api_handler_telegram_webhook_newtelegramwebhookhandler", "target": "inbounddeduprepository", "relation": "references", "confidence": "EXTRACTED", "source_file": "internal/api/handler/telegram_webhook.go", "source_location": "L39", "weight": 1.0, "context": "parameter_type"}, {"source": "home_pablo_coding_pergo_internal_api_handler_telegram_webhook_newtelegramwebhookhandler", "target": "s3client", "relation": "references", "confidence": "EXTRACTED", "source_file": "internal/api/handler/telegram_webhook.go", "source_location": "L39", "weight": 1.0, "context": "parameter_type"}, {"source": "home_pablo_coding_pergo_internal_api_handler_telegram_webhook_newtelegramwebhookhandler", "target": "jetstreampublisher", "relation": "references", "confidence": "EXTRACTED", "source_file": "internal/api/handler/telegram_webhook.go", "source_location": "L39", "weight": 1.0, "context": "parameter_type"}, {"source": "home_pablo_coding_pergo_internal_api_handler_telegram_webhook_newtelegramwebhookhandler", "target": "writer", "relation": "references", "confidence": "EXTRACTED", "source_file": "internal/api/handler/telegram_webhook.go", "source_location": "L39", "weight": 1.0, "context": "parameter_type"}, {"source": "home_pablo_coding_pergo_internal_api_handler_telegram_webhook_newtelegramwebhookhandler", "target": "handler_telegramwebhookhandler", "relation": "references", "confidence": "EXTRACTED", "source_file": "internal/api/handler/telegram_webhook.go", "source_location": "L39", "weight": 1.0, "context": "return_type"}, {"source": "handler_telegramwebhookhandler", "target": "handler_telegramwebhookhandler_setbaseurl", "relation": "method", "confidence": "EXTRACTED", "source_file": "internal/api/handler/telegram_webhook.go", "source_location": "L62", "weight": 1.0}, {"source": "home_pablo_coding_pergo_internal_api_handler_telegram_webhook_go", "target": "handler_telegramupdate", "relation": "contains", "confidence": "EXTRACTED", "source_file": "internal/api/handler/telegram_webhook.go", "source_location": "L66", "weight": 1.0}, {"source": "handler_telegramupdate", "target": "telegrammessage", "relation": "references", "confidence": "EXTRACTED", "source_file": "internal/api/handler/telegram_webhook.go", "source_location": "L68", "weight": 1.0, "context": "field"}, {"source": "home_pablo_coding_pergo_internal_api_handler_telegram_webhook_go", "target": "handler_telegrammessage", "relation": "contains", "confidence": "EXTRACTED", "source_file": "internal/api/handler/telegram_webhook.go", "source_location": "L71", "weight": 1.0}, {"source": "handler_telegrammessage", "target": "telegramchat", "relation": "references", "confidence": "EXTRACTED", "source_file": "internal/api/handler/telegram_webhook.go", "source_location": "L73", "weight": 1.0, "context": "field"}, {"source": "handler_telegrammessage", "target": "telegramphoto", "relation": "references", "confidence": "EXTRACTED", "source_file": "internal/api/handler/telegram_webhook.go", "source_location": "L76", "weight": 1.0, "context": "field"}, {"source": "handler_telegrammessage", "target": "telegramdocument", "relation": "references", "confidence": "EXTRACTED", "source_file": "internal/api/handler/telegram_webhook.go", "source_location": "L77", "weight": 1.0, "context": "field"}, {"source": "handler_telegrammessage", "target": "telegramaudio", "relation": "references", "confidence": "EXTRACTED", "source_file": "internal/api/handler/telegram_webhook.go", "source_location": "L78", "weight": 1.0, "context": "field"}, {"source": "handler_telegrammessage", "target": "telegramvideo", "relation": "references", "confidence": "EXTRACTED", "source_file": "internal/api/handler/telegram_webhook.go", "source_location": "L79", "weight": 1.0, "context": "field"}, {"source": "handler_telegrammessage", "target": "telegramlocation", "relation": "references", "confidence": "EXTRACTED", "source_file": "internal/api/handler/telegram_webhook.go", "source_location": "L80", "weight": 1.0, "context": "field"}, {"source": "handler_telegrammessage", "target": "telegramcontact", "relation": "references", "confidence": "EXTRACTED", "source_file": "internal/api/handler/telegram_webhook.go", "source_location": "L81", "weight": 1.0, "context": "field"}, {"source": "home_pablo_coding_pergo_internal_api_handler_telegram_webhook_go", "target": "handler_telegramphoto", "relation": "contains", "confidence": "EXTRACTED", "source_file": "internal/api/handler/telegram_webhook.go", "source_location": "L84", "weight": 1.0}, {"source": "home_pablo_coding_pergo_internal_api_handler_telegram_webhook_go", "target": "handler_telegramdocument", "relation": "contains", "confidence": "EXTRACTED", "source_file": "internal/api/handler/telegram_webhook.go", "source_location": "L89", "weight": 1.0}, {"source": "home_pablo_coding_pergo_internal_api_handler_telegram_webhook_go", "target": "handler_telegramaudio", "relation": "contains", "confidence": "EXTRACTED", "source_file": "internal/api/handler/telegram_webhook.go", "source_location": "L95", "weight": 1.0}, {"source": "home_pablo_coding_pergo_internal_api_handler_telegram_webhook_go", "target": "handler_telegramvideo", "relation": "contains", "confidence": "EXTRACTED", "source_file": "internal/api/handler/telegram_webhook.go", "source_location": "L100", "weight": 1.0}, {"source": "home_pablo_coding_pergo_internal_api_handler_telegram_webhook_go", "target": "handler_telegramlocation", "relation": "contains", "confidence": "EXTRACTED", "source_file": "internal/api/handler/telegram_webhook.go", "source_location": "L105", "weight": 1.0}, {"source": "home_pablo_coding_pergo_internal_api_handler_telegram_webhook_go", "target": "handler_telegramcontact", "relation": "contains", "confidence": "EXTRACTED", "source_file": "internal/api/handler/telegram_webhook.go", "source_location": "L110", "weight": 1.0}, {"source": "home_pablo_coding_pergo_internal_api_handler_telegram_webhook_go", "target": "handler_telegramchat", "relation": "contains", "confidence": "EXTRACTED", "source_file": "internal/api/handler/telegram_webhook.go", "source_location": "L116", "weight": 1.0}, {"source": "home_pablo_coding_pergo_internal_api_handler_telegram_webhook_go", "target": "handler_telegramconfig", "relation": "contains", "confidence": "EXTRACTED", "source_file": "internal/api/handler/telegram_webhook.go", "source_location": "L120", "weight": 1.0}, {"source": "handler_telegramwebhookhandler", "target": "handler_telegramwebhookhandler_handle", "relation": "method", "confidence": "EXTRACTED", "source_file": "internal/api/handler/telegram_webhook.go", "source_location": "L126", "weight": 1.0}, {"source": "handler_telegramwebhookhandler_handle", "target": "context", "relation": "references", "confidence": "EXTRACTED", "source_file": "internal/api/handler/telegram_webhook.go", "source_location": "L126", "weight": 1.0, "context": "parameter_type"}, {"source": "handler_telegramwebhookhandler", "target": "handler_telegramwebhookhandler_downloadtelegramfile", "relation": "method", "confidence": "EXTRACTED", "source_file": "internal/api/handler/telegram_webhook.go", "source_location": "L305", "weight": 1.0}, {"source": "handler_telegramwebhookhandler_downloadtelegramfile", "target": "context", "relation": "references", "confidence": "EXTRACTED", "source_file": "internal/api/handler/telegram_webhook.go", "source_location": "L305", "weight": 1.0, "context": "parameter_type"}, {"source": "home_pablo_coding_pergo_internal_api_handler_telegram_webhook_go", "target": "home_pablo_coding_pergo_internal_api_handler_telegram_webhook_sha256hash", "relation": "contains", "confidence": "EXTRACTED", "source_file": "internal/api/handler/telegram_webhook.go", "source_location": "L364", "weight": 1.0}, {"source": "handler_telegramwebhookhandler_handle", "target": "context", "relation": "calls", "context": "call", "confidence": "EXTRACTED", "source_file": "internal/api/handler/telegram_webhook.go", "source_location": "L144", "weight": 1.0}, {"source": "handler_telegramwebhookhandler_handle", "target": "handler_telegramwebhookhandler_downloadtelegramfile", "relation": "calls", "context": "call", "confidence": "EXTRACTED", "source_file": "internal/api/handler/telegram_webhook.go", "source_location": "L238", "weight": 1.0}, {"source": "handler_telegramwebhookhandler_handle", "target": "home_pablo_coding_pergo_internal_api_handler_telegram_webhook_sha256hash", "relation": "calls", "context": "call", "confidence": "EXTRACTED", "source_file": "internal/api/handler/telegram_webhook.go", "source_location": "L249", "weight": 1.0}], "raw_calls": [{"caller_nid": "handler_telegramwebhookhandler_handle", "callee": "NoContent", "is_member_call": true, "source_file": "/home/pablo/Coding/PerGo/internal/api/handler/telegram_webhook.go", "source_location": "L129"}, {"caller_nid": "handler_telegramwebhookhandler_handle", "callee": "Parse", "is_member_call": false, "source_file": "/home/pablo/Coding/PerGo/internal/api/handler/telegram_webhook.go", "source_location": "L132"}, {"caller_nid": "handler_telegramwebhookhandler_handle", "callee": "NoContent", "is_member_call": true, "source_file": "/home/pablo/Coding/PerGo/internal/api/handler/telegram_webhook.go", "source_location": "L134"}, {"caller_nid": "handler_telegramwebhookhandler_handle", "callee": "Get", "is_member_call": true, "source_file": "/home/pablo/Coding/PerGo/internal/api/handler/telegram_webhook.go", "source_location": "L138"}, {"caller_nid": "handler_telegramwebhookhandler_handle", "callee": "NoContent", "is_member_call": true, "source_file": "/home/pablo/Coding/PerGo/internal/api/handler/telegram_webhook.go", "source_location": "L140"}, {"caller_nid": "handler_telegramwebhookhandler_handle", "callee": "Get", "is_member_call": true, "source_file": "/home/pablo/Coding/PerGo/internal/api/handler/telegram_webhook.go", "source_location": "L144"}, {"caller_nid": "handler_telegramwebhookhandler_handle", "callee": "NoContent", "is_member_call": true, "source_file": "/home/pablo/Coding/PerGo/internal/api/handler/telegram_webhook.go", "source_location": "L146"}, {"caller_nid": "handler_telegramwebhookhandler_handle", "callee": "Unmarshal", "is_member_call": false, "source_file": "/home/pablo/Coding/PerGo/internal/api/handler/telegram_webhook.go", "source_location": "L150"}, {"caller_nid": "handler_telegramwebhookhandler_handle", "callee": "NoContent", "is_member_call": true, "source_file": "/home/pablo/Coding/PerGo/internal/api/handler/telegram_webhook.go", "source_location": "L151"}, {"caller_nid": "handler_telegramwebhookhandler_handle", "callee": "NoContent", "is_member_call": true, "source_file": "/home/pablo/Coding/PerGo/internal/api/handler/telegram_webhook.go", "source_location": "L156"}, {"caller_nid": "handler_telegramwebhookhandler_handle", "callee": "Bind", "is_member_call": true, "source_file": "/home/pablo/Coding/PerGo/internal/api/handler/telegram_webhook.go", "source_location": "L161"}, {"caller_nid": "handler_telegramwebhookhandler_handle", "callee": "NoContent", "is_member_call": true, "source_file": "/home/pablo/Coding/PerGo/internal/api/handler/telegram_webhook.go", "source_location": "L162"}, {"caller_nid": "handler_telegramwebhookhandler_handle", "callee": "FormatInt", "is_member_call": false, "source_file": "/home/pablo/Coding/PerGo/internal/api/handler/telegram_webhook.go", "source_location": "L168"}, {"caller_nid": "handler_telegramwebhookhandler_handle", "callee": "InsertAndCheck", "is_member_call": true, "source_file": "/home/pablo/Coding/PerGo/internal/api/handler/telegram_webhook.go", "source_location": "L172"}, {"caller_nid": "handler_telegramwebhookhandler_handle", "callee": "FormatInt", "is_member_call": false, "source_file": "/home/pablo/Coding/PerGo/internal/api/handler/telegram_webhook.go", "source_location": "L172"}, {"caller_nid": "handler_telegramwebhookhandler_handle", "callee": "NoContent", "is_member_call": true, "source_file": "/home/pablo/Coding/PerGo/internal/api/handler/telegram_webhook.go", "source_location": "L175"}, {"caller_nid": "handler_telegramwebhookhandler_handle", "callee": "Info", "is_member_call": false, "source_file": "/home/pablo/Coding/PerGo/internal/api/handler/telegram_webhook.go", "source_location": "L178"}, {"caller_nid": "handler_telegramwebhookhandler_handle", "callee": "NoContent", "is_member_call": true, "source_file": "/home/pablo/Coding/PerGo/internal/api/handler/telegram_webhook.go", "source_location": "L179"}, {"caller_nid": "handler_telegramwebhookhandler_handle", "callee": "Upsert", "is_member_call": true, "source_file": "/home/pablo/Coding/PerGo/internal/api/handler/telegram_webhook.go", "source_location": "L184"}, {"caller_nid": "handler_telegramwebhookhandler_handle", "callee": "UTC", "is_member_call": true, "source_file": "/home/pablo/Coding/PerGo/internal/api/handler/telegram_webhook.go", "source_location": "L184"}, {"caller_nid": "handler_telegramwebhookhandler_handle", "callee": "Now", "is_member_call": false, "source_file": "/home/pablo/Coding/PerGo/internal/api/handler/telegram_webhook.go", "source_location": "L184"}, {"caller_nid": "handler_telegramwebhookhandler_handle", "callee": "GetByID", "is_member_call": true, "source_file": "/home/pablo/Coding/PerGo/internal/api/handler/telegram_webhook.go", "source_location": "L189"}, {"caller_nid": "handler_telegramwebhookhandler_handle", "callee": "NoContent", "is_member_call": true, "source_file": "/home/pablo/Coding/PerGo/internal/api/handler/telegram_webhook.go", "source_location": "L191"}, {"caller_nid": "handler_telegramwebhookhandler_handle", "callee": "New", "is_member_call": false, "source_file": "/home/pablo/Coding/PerGo/internal/api/handler/telegram_webhook.go", "source_location": "L195"}, {"caller_nid": "handler_telegramwebhookhandler_handle", "callee": "FormatInt", "is_member_call": false, "source_file": "/home/pablo/Coding/PerGo/internal/api/handler/telegram_webhook.go", "source_location": "L199"}, {"caller_nid": "handler_telegramwebhookhandler_handle", "callee": "Format", "is_member_call": true, "source_file": "/home/pablo/Coding/PerGo/internal/api/handler/telegram_webhook.go", "source_location": "L201"}, {"caller_nid": "handler_telegramwebhookhandler_handle", "callee": "UTC", "is_member_call": true, "source_file": "/home/pablo/Coding/PerGo/internal/api/handler/telegram_webhook.go", "source_location": "L201"}, {"caller_nid": "handler_telegramwebhookhandler_handle", "callee": "Now", "is_member_call": false, "source_file": "/home/pablo/Coding/PerGo/internal/api/handler/telegram_webhook.go", "source_location": "L201"}, {"caller_nid": "handler_telegramwebhookhandler_handle", "callee": "Split", "is_member_call": false, "source_file": "/home/pablo/Coding/PerGo/internal/api/handler/telegram_webhook.go", "source_location": "L244"}, {"caller_nid": "handler_telegramwebhookhandler_handle", "callee": "Sprintf", "is_member_call": false, "source_file": "/home/pablo/Coding/PerGo/internal/api/handler/telegram_webhook.go", "source_location": "L250"}, {"caller_nid": "handler_telegramwebhookhandler_handle", "callee": "Upload", "is_member_call": true, "source_file": "/home/pablo/Coding/PerGo/internal/api/handler/telegram_webhook.go", "source_location": "L251"}, {"caller_nid": "handler_telegramwebhookhandler_handle", "callee": "Sprintf", "is_member_call": false, "source_file": "/home/pablo/Coding/PerGo/internal/api/handler/telegram_webhook.go", "source_location": "L254"}, {"caller_nid": "handler_telegramwebhookhandler_handle", "callee": "NoContent", "is_member_call": true, "source_file": "/home/pablo/Coding/PerGo/internal/api/handler/telegram_webhook.go", "source_location": "L287"}, {"caller_nid": "handler_telegramwebhookhandler_handle", "callee": "Marshal", "is_member_call": false, "source_file": "/home/pablo/Coding/PerGo/internal/api/handler/telegram_webhook.go", "source_location": "L292"}, {"caller_nid": "handler_telegramwebhookhandler_handle", "callee": "Sprintf", "is_member_call": false, "source_file": "/home/pablo/Coding/PerGo/internal/api/handler/telegram_webhook.go", "source_location": "L293"}, {"caller_nid": "handler_telegramwebhookhandler_handle", "callee": "Publish", "is_member_call": true, "source_file": "/home/pablo/Coding/PerGo/internal/api/handler/telegram_webhook.go", "source_location": "L294"}, {"caller_nid": "handler_telegramwebhookhandler_handle", "callee": "Write", "is_member_call": true, "source_file": "/home/pablo/Coding/PerGo/internal/api/handler/telegram_webhook.go", "source_location": "L297"}, {"caller_nid": "handler_telegramwebhookhandler_handle", "callee": "NewEvent", "is_member_call": false, "source_file": "/home/pablo/Coding/PerGo/internal/api/handler/telegram_webhook.go", "source_location": "L297"}, {"caller_nid": "handler_telegramwebhookhandler_handle", "callee": "NoContent", "is_member_call": true, "source_file": "/home/pablo/Coding/PerGo/internal/api/handler/telegram_webhook.go", "source_location": "L302"}, {"caller_nid": "handler_telegramwebhookhandler_downloadtelegramfile", "callee": "Sprintf", "is_member_call": false, "source_file": "/home/pablo/Coding/PerGo/internal/api/handler/telegram_webhook.go", "source_location": "L307"}, {"caller_nid": "handler_telegramwebhookhandler_downloadtelegramfile", "callee": "NewRequestWithContext", "is_member_call": false, "source_file": "/home/pablo/Coding/PerGo/internal/api/handler/telegram_webhook.go", "source_location": "L308"}, {"caller_nid": "handler_telegramwebhookhandler_downloadtelegramfile", "callee": "Do", "is_member_call": true, "source_file": "/home/pablo/Coding/PerGo/internal/api/handler/telegram_webhook.go", "source_location": "L313"}, {"caller_nid": "handler_telegramwebhookhandler_downloadtelegramfile", "callee": "Close", "is_member_call": true, "source_file": "/home/pablo/Coding/PerGo/internal/api/handler/telegram_webhook.go", "source_location": "L317"}, {"caller_nid": "handler_telegramwebhookhandler_downloadtelegramfile", "callee": "Errorf", "is_member_call": false, "source_file": "/home/pablo/Coding/PerGo/internal/api/handler/telegram_webhook.go", "source_location": "L320"}, {"caller_nid": "handler_telegramwebhookhandler_downloadtelegramfile", "callee": "Decode", "is_member_call": true, "source_file": "/home/pablo/Coding/PerGo/internal/api/handler/telegram_webhook.go", "source_location": "L330"}, {"caller_nid": "handler_telegramwebhookhandler_downloadtelegramfile", "callee": "NewDecoder", "is_member_call": false, "source_file": "/home/pablo/Coding/PerGo/internal/api/handler/telegram_webhook.go", "source_location": "L330"}, {"caller_nid": "handler_telegramwebhookhandler_downloadtelegramfile", "callee": "Errorf", "is_member_call": false, "source_file": "/home/pablo/Coding/PerGo/internal/api/handler/telegram_webhook.go", "source_location": "L331"}, {"caller_nid": "handler_telegramwebhookhandler_downloadtelegramfile", "callee": "Sprintf", "is_member_call": false, "source_file": "/home/pablo/Coding/PerGo/internal/api/handler/telegram_webhook.go", "source_location": "L335"}, {"caller_nid": "handler_telegramwebhookhandler_downloadtelegramfile", "callee": "NewRequestWithContext", "is_member_call": false, "source_file": "/home/pablo/Coding/PerGo/internal/api/handler/telegram_webhook.go", "source_location": "L336"}, {"caller_nid": "handler_telegramwebhookhandler_downloadtelegramfile", "callee": "Do", "is_member_call": true, "source_file": "/home/pablo/Coding/PerGo/internal/api/handler/telegram_webhook.go", "source_location": "L341"}, {"caller_nid": "handler_telegramwebhookhandler_downloadtelegramfile", "callee": "Close", "is_member_call": true, "source_file": "/home/pablo/Coding/PerGo/internal/api/handler/telegram_webhook.go", "source_location": "L345"}, {"caller_nid": "handler_telegramwebhookhandler_downloadtelegramfile", "callee": "Errorf", "is_member_call": false, "source_file": "/home/pablo/Coding/PerGo/internal/api/handler/telegram_webhook.go", "source_location": "L348"}, {"caller_nid": "handler_telegramwebhookhandler_downloadtelegramfile", "callee": "LimitReader", "is_member_call": false, "source_file": "/home/pablo/Coding/PerGo/internal/api/handler/telegram_webhook.go", "source_location": "L351"}, {"caller_nid": "handler_telegramwebhookhandler_downloadtelegramfile", "callee": "ReadAll", "is_member_call": false, "source_file": "/home/pablo/Coding/PerGo/internal/api/handler/telegram_webhook.go", "source_location": "L352"}, {"caller_nid": "handler_telegramwebhookhandler_downloadtelegramfile", "callee": "New", "is_member_call": false, "source_file": "/home/pablo/Coding/PerGo/internal/api/handler/telegram_webhook.go", "source_location": "L358"}, {"caller_nid": "home_pablo_coding_pergo_internal_api_handler_telegram_webhook_sha256hash", "callee": "New", "is_member_call": false, "source_file": "/home/pablo/Coding/PerGo/internal/api/handler/telegram_webhook.go", "source_location": "L365"}, {"caller_nid": "home_pablo_coding_pergo_internal_api_handler_telegram_webhook_sha256hash", "callee": "Write", "is_member_call": true, "source_file": "/home/pablo/Coding/PerGo/internal/api/handler/telegram_webhook.go", "source_location": "L366"}, {"caller_nid": "home_pablo_coding_pergo_internal_api_handler_telegram_webhook_sha256hash", "callee": "EncodeToString", "is_member_call": false, "source_file": "/home/pablo/Coding/PerGo/internal/api/handler/telegram_webhook.go", "source_location": "L367"}, {"caller_nid": "home_pablo_coding_pergo_internal_api_handler_telegram_webhook_sha256hash", "callee": "Sum", "is_member_call": true, "source_file": "/home/pablo/Coding/PerGo/internal/api/handler/telegram_webhook.go", "source_location": "L367"}]}