{"nodes": [{"id": "home_pablo_coding_omnigo_planning_research_architecture_md", "label": "ARCHITECTURE.md", "file_type": "document", "source_file": ".planning/research/ARCHITECTURE.md", "source_location": "L1"}, {"id": "research_architecture_architecture_research", "label": "Architecture Research", "file_type": "document", "source_file": ".planning/research/ARCHITECTURE.md", "source_location": "L1"}, {"id": "research_architecture_purpose_of_this_document", "label": "Purpose of this document", "file_type": "document", "source_file": ".planning/research/ARCHITECTURE.md", "source_location": "L7"}, {"id": "research_architecture_standard_architecture", "label": "Standard Architecture", "file_type": "document", "source_file": ".planning/research/ARCHITECTURE.md", "source_location": "L17"}, {"id": "research_architecture_system_overview", "label": "System Overview", "file_type": "document", "source_file": ".planning/research/ARCHITECTURE.md", "source_location": "L19"}, {"id": "research_architecture_component_responsibilities", "label": "Component Responsibilities", "file_type": "document", "source_file": ".planning/research/ARCHITECTURE.md", "source_location": "L72"}, {"id": "research_architecture_recommended_project_structure", "label": "Recommended Project Structure", "file_type": "document", "source_file": ".planning/research/ARCHITECTURE.md", "source_location": "L89"}, {"id": "research_architecture_structure_rationale", "label": "Structure rationale", "file_type": "document", "source_file": ".planning/research/ARCHITECTURE.md", "source_location": "L129"}, {"id": "research_architecture_architectural_patterns", "label": "Architectural Patterns", "file_type": "document", "source_file": ".planning/research/ARCHITECTURE.md", "source_location": "L140"}, {"id": "research_architecture_pattern_1_durable_work_queue_boundary_nats_jetstream_workqueuepolicy", "label": "Pattern 1: Durable work-queue boundary (NATS JetStream `WorkQueuePolicy`)", "file_type": "document", "source_file": ".planning/research/ARCHITECTURE.md", "source_location": "L142"}, {"id": "research_architecture_pattern_2_two_i_o_hot_path", "label": "Pattern 2: Two-I/O hot path", "file_type": "document", "source_file": ".planning/research/ARCHITECTURE.md", "source_location": "L164"}, {"id": "research_architecture_pattern_3_sequential_fallback_pipeline", "label": "Pattern 3: Sequential fallback pipeline", "file_type": "document", "source_file": ".planning/research/ARCHITECTURE.md", "source_location": "L175"}, {"id": "research_architecture_pattern_4_bounded_buffer_audit_fan_in_non_blocking_on_hot_path", "label": "Pattern 4: Bounded-buffer audit fan-in (non-blocking on hot path)", "file_type": "document", "source_file": ".planning/research/ARCHITECTURE.md", "source_location": "L188"}, {"id": "research_architecture_pattern_5_per_session_rate_limited_goroutine_staggered_dispatch", "label": "Pattern 5: Per-session rate-limited goroutine (staggered dispatch)", "file_type": "document", "source_file": ".planning/research/ARCHITECTURE.md", "source_location": "L204"}, {"id": "research_architecture_pattern_6_consumer_side_dispatcher_interface_plugin_boundary", "label": "Pattern 6: Consumer-side `Dispatcher` interface (plugin boundary)", "file_type": "document", "source_file": ".planning/research/ARCHITECTURE.md", "source_location": "L216"}, {"id": "research_architecture_pattern_7_workqueuepolicy_single_consumer_topology_decision", "label": "Pattern 7: WorkQueuePolicy single-consumer topology decision", "file_type": "document", "source_file": ".planning/research/ARCHITECTURE.md", "source_location": "L226"}, {"id": "research_architecture_data_flow", "label": "Data Flow", "file_type": "document", "source_file": ".planning/research/ARCHITECTURE.md", "source_location": "L251"}, {"id": "research_architecture_ingest_broker_worker_channel_audit", "label": "Ingest \u2192 broker \u2192 worker \u2192 channel \u2192 audit", "file_type": "document", "source_file": ".planning/research/ARCHITECTURE.md", "source_location": "L253"}, {"id": "research_architecture_trace_id_propagation_4_boundaries_the_100_correlation_slo", "label": "Trace-ID propagation (4 boundaries \u2014 the 100% correlation SLO)", "file_type": "document", "source_file": ".planning/research/ARCHITECTURE.md", "source_location": "L291"}, {"id": "research_architecture_webhook_delivery_flow_separate_durable_stream", "label": "Webhook delivery flow (separate durable stream)", "file_type": "document", "source_file": ".planning/research/ARCHITECTURE.md", "source_location": "L304"}, {"id": "research_architecture_concurrency_model_validation", "label": "Concurrency Model Validation", "file_type": "document", "source_file": ".planning/research/ARCHITECTURE.md", "source_location": "L314"}, {"id": "research_architecture_suggested_build_order_milestone_validation_refinement", "label": "Suggested Build Order (milestone validation & refinement)", "file_type": "document", "source_file": ".planning/research/ARCHITECTURE.md", "source_location": "L334"}, {"id": "research_architecture_milestone_1_core_foundation_weeks_1_3_validated_minor_refinement", "label": "Milestone 1 \u2014 Core Foundation (weeks 1\u20133) \u2705 validated, minor refinement", "file_type": "document", "source_file": ".planning/research/ARCHITECTURE.md", "source_location": "L339"}, {"id": "research_architecture_milestone_2_queue_whatsapp_web_weeks_4_6_validated_key_refinements", "label": "Milestone 2 \u2014 Queue & WhatsApp Web (weeks 4\u20136) \u2705 validated, key refinements", "file_type": "document", "source_file": ".planning/research/ARCHITECTURE.md", "source_location": "L360"}, {"id": "research_architecture_milestone_3_official_channels_fallback_weeks_7_8_validated", "label": "Milestone 3 \u2014 Official Channels & Fallback (weeks 7\u20138) \u2705 validated", "file_type": "document", "source_file": ".planning/research/ARCHITECTURE.md", "source_location": "L383"}, {"id": "research_architecture_missing_components_structural_gaps", "label": "Missing Components & Structural Gaps", "file_type": "document", "source_file": ".planning/research/ARCHITECTURE.md", "source_location": "L403"}, {"id": "research_architecture_gap_1_publish_side_idempotency_via_nats_msg_id_high_impact_low_effort", "label": "GAP 1 \u2014 Publish-side idempotency via `Nats-Msg-Id` (HIGH impact, LOW effort)", "file_type": "document", "source_file": ".planning/research/ARCHITECTURE.md", "source_location": "L408"}, {"id": "research_architecture_gap_2_native_per_subject_backpressure_via_maxmsgspersubject_discardnewpersubject_high_impact_low_effort", "label": "GAP 2 \u2014 Native per-subject backpressure via `MaxMsgsPerSubject` + `DiscardNewPerSubject` (HIGH impact, LOW effort)", "file_type": "document", "source_file": ".planning/research/ARCHITECTURE.md", "source_location": "L415"}, {"id": "research_architecture_gap_3_no_automatic_dead_letter_for_the_messages_stream_medium_impact_medium_effort", "label": "GAP 3 \u2014 No automatic dead-letter for the messages stream (MEDIUM impact, MEDIUM effort)", "file_type": "document", "source_file": ".planning/research/ARCHITECTURE.md", "source_location": "L423"}, {"id": "research_architecture_gap_4_two_driver_stacks_and_two_migration_systems_medium_impact_low_effort_documentation_structure", "label": "GAP 4 \u2014 Two driver stacks and two migration systems (MEDIUM impact, LOW effort \u2014 documentation/structure)", "file_type": "document", "source_file": ".planning/research/ARCHITECTURE.md", "source_location": "L431"}, {"id": "research_architecture_gap_5_startup_reconnect_storm_protection_high_impact_low_effort", "label": "GAP 5 \u2014 Startup reconnect-storm protection (HIGH impact, LOW effort)", "file_type": "document", "source_file": ".planning/research/ARCHITECTURE.md", "source_location": "L441"}, {"id": "research_architecture_gap_6_whatsapp_web_version_auto_refresh_medium_impact_low_effort", "label": "GAP 6 \u2014 WhatsApp Web version auto-refresh (MEDIUM impact, LOW effort)", "file_type": "document", "source_file": ".planning/research/ARCHITECTURE.md", "source_location": "L450"}, {"id": "research_architecture_gap_7_workqueue_single_consumer_topology_must_be_documented_low_impact_documentation", "label": "GAP 7 \u2014 WorkQueue single-consumer topology must be documented (LOW impact, documentation)", "file_type": "document", "source_file": ".planning/research/ARCHITECTURE.md", "source_location": "L457"}, {"id": "research_architecture_gap_8_copyfrom_is_connection_level_not_pool_level_low_impact_implementation_detail", "label": "GAP 8 \u2014 `CopyFrom` is connection-level, not pool-level (LOW impact, implementation detail)", "file_type": "document", "source_file": ".planning/research/ARCHITECTURE.md", "source_location": "L464"}, {"id": "research_architecture_gap_9_getdevice_requires_an_ad_jid_low_impact_implementation_detail", "label": "GAP 9 \u2014 `GetDevice` requires an AD-JID (LOW impact, implementation detail)", "file_type": "document", "source_file": ".planning/research/ARCHITECTURE.md", "source_location": "L470"}, {"id": "research_architecture_gap_10_idempotency_at_the_provider_boundary_medium_impact_design_decision", "label": "GAP 10 \u2014 Idempotency at the provider boundary (MEDIUM impact, design decision)", "file_type": "document", "source_file": ".planning/research/ARCHITECTURE.md", "source_location": "L476"}, {"id": "research_architecture_scaling_considerations", "label": "Scaling Considerations", "file_type": "document", "source_file": ".planning/research/ARCHITECTURE.md", "source_location": "L487"}, {"id": "research_architecture_scaling_priorities_in_order_of_what_breaks_first", "label": "Scaling priorities (in order of what breaks first)", "file_type": "document", "source_file": ".planning/research/ARCHITECTURE.md", "source_location": "L495"}, {"id": "research_architecture_anti_patterns_to_avoid", "label": "Anti-Patterns to Avoid", "file_type": "document", "source_file": ".planning/research/ARCHITECTURE.md", "source_location": "L509"}, {"id": "research_architecture_integration_points", "label": "Integration Points", "file_type": "document", "source_file": ".planning/research/ARCHITECTURE.md", "source_location": "L524"}, {"id": "research_architecture_external_services", "label": "External services", "file_type": "document", "source_file": ".planning/research/ARCHITECTURE.md", "source_location": "L526"}, {"id": "research_architecture_internal_boundaries", "label": "Internal boundaries", "file_type": "document", "source_file": ".planning/research/ARCHITECTURE.md", "source_location": "L537"}, {"id": "research_architecture_sources", "label": "Sources", "file_type": "document", "source_file": ".planning/research/ARCHITECTURE.md", "source_location": "L551"}], "edges": [{"source": "home_pablo_coding_omnigo_planning_research_architecture_md", "target": "research_architecture_architecture_research", "relation": "contains", "confidence": "EXTRACTED", "source_file": ".planning/research/ARCHITECTURE.md", "source_location": "L1", "weight": 1.0}, {"source": "research_architecture_architecture_research", "target": "research_architecture_purpose_of_this_document", "relation": "contains", "confidence": "EXTRACTED", "source_file": ".planning/research/ARCHITECTURE.md", "source_location": "L7", "weight": 1.0}, {"source": "research_architecture_architecture_research", "target": "research_architecture_standard_architecture", "relation": "contains", "confidence": "EXTRACTED", "source_file": ".planning/research/ARCHITECTURE.md", "source_location": "L17", "weight": 1.0}, {"source": "research_architecture_standard_architecture", "target": "research_architecture_system_overview", "relation": "contains", "confidence": "EXTRACTED", "source_file": ".planning/research/ARCHITECTURE.md", "source_location": "L19", "weight": 1.0}, {"source": "research_architecture_standard_architecture", "target": "research_architecture_component_responsibilities", "relation": "contains", "confidence": "EXTRACTED", "source_file": ".planning/research/ARCHITECTURE.md", "source_location": "L72", "weight": 1.0}, {"source": "research_architecture_architecture_research", "target": "research_architecture_recommended_project_structure", "relation": "contains", "confidence": "EXTRACTED", "source_file": ".planning/research/ARCHITECTURE.md", "source_location": "L89", "weight": 1.0}, {"source": "research_architecture_recommended_project_structure", "target": "research_architecture_structure_rationale", "relation": "contains", "confidence": "EXTRACTED", "source_file": ".planning/research/ARCHITECTURE.md", "source_location": "L129", "weight": 1.0}, {"source": "research_architecture_architecture_research", "target": "research_architecture_architectural_patterns", "relation": "contains", "confidence": "EXTRACTED", "source_file": ".planning/research/ARCHITECTURE.md", "source_location": "L140", "weight": 1.0}, {"source": "research_architecture_architectural_patterns", "target": "research_architecture_pattern_1_durable_work_queue_boundary_nats_jetstream_workqueuepolicy", "relation": "contains", "confidence": "EXTRACTED", "source_file": ".planning/research/ARCHITECTURE.md", "source_location": "L142", "weight": 1.0}, {"source": "research_architecture_architectural_patterns", "target": "research_architecture_pattern_2_two_i_o_hot_path", "relation": "contains", "confidence": "EXTRACTED", "source_file": ".planning/research/ARCHITECTURE.md", "source_location": "L164", "weight": 1.0}, {"source": "research_architecture_architectural_patterns", "target": "research_architecture_pattern_3_sequential_fallback_pipeline", "relation": "contains", "confidence": "EXTRACTED", "source_file": ".planning/research/ARCHITECTURE.md", "source_location": "L175", "weight": 1.0}, {"source": "research_architecture_architectural_patterns", "target": "research_architecture_pattern_4_bounded_buffer_audit_fan_in_non_blocking_on_hot_path", "relation": "contains", "confidence": "EXTRACTED", "source_file": ".planning/research/ARCHITECTURE.md", "source_location": "L188", "weight": 1.0}, {"source": "research_architecture_architectural_patterns", "target": "research_architecture_pattern_5_per_session_rate_limited_goroutine_staggered_dispatch", "relation": "contains", "confidence": "EXTRACTED", "source_file": ".planning/research/ARCHITECTURE.md", "source_location": "L204", "weight": 1.0}, {"source": "research_architecture_architectural_patterns", "target": "research_architecture_pattern_6_consumer_side_dispatcher_interface_plugin_boundary", "relation": "contains", "confidence": "EXTRACTED", "source_file": ".planning/research/ARCHITECTURE.md", "source_location": "L216", "weight": 1.0}, {"source": "research_architecture_architectural_patterns", "target": "research_architecture_pattern_7_workqueuepolicy_single_consumer_topology_decision", "relation": "contains", "confidence": "EXTRACTED", "source_file": ".planning/research/ARCHITECTURE.md", "source_location": "L226", "weight": 1.0}, {"source": "research_architecture_architecture_research", "target": "research_architecture_data_flow", "relation": "contains", "confidence": "EXTRACTED", "source_file": ".planning/research/ARCHITECTURE.md", "source_location": "L251", "weight": 1.0}, {"source": "research_architecture_data_flow", "target": "research_architecture_ingest_broker_worker_channel_audit", "relation": "contains", "confidence": "EXTRACTED", "source_file": ".planning/research/ARCHITECTURE.md", "source_location": "L253", "weight": 1.0}, {"source": "research_architecture_data_flow", "target": "research_architecture_trace_id_propagation_4_boundaries_the_100_correlation_slo", "relation": "contains", "confidence": "EXTRACTED", "source_file": ".planning/research/ARCHITECTURE.md", "source_location": "L291", "weight": 1.0}, {"source": "research_architecture_data_flow", "target": "research_architecture_webhook_delivery_flow_separate_durable_stream", "relation": "contains", "confidence": "EXTRACTED", "source_file": ".planning/research/ARCHITECTURE.md", "source_location": "L304", "weight": 1.0}, {"source": "research_architecture_architecture_research", "target": "research_architecture_concurrency_model_validation", "relation": "contains", "confidence": "EXTRACTED", "source_file": ".planning/research/ARCHITECTURE.md", "source_location": "L314", "weight": 1.0}, {"source": "research_architecture_architecture_research", "target": "research_architecture_suggested_build_order_milestone_validation_refinement", "relation": "contains", "confidence": "EXTRACTED", "source_file": ".planning/research/ARCHITECTURE.md", "source_location": "L334", "weight": 1.0}, {"source": "research_architecture_suggested_build_order_milestone_validation_refinement", "target": "research_architecture_milestone_1_core_foundation_weeks_1_3_validated_minor_refinement", "relation": "contains", "confidence": "EXTRACTED", "source_file": ".planning/research/ARCHITECTURE.md", "source_location": "L339", "weight": 1.0}, {"source": "research_architecture_suggested_build_order_milestone_validation_refinement", "target": "research_architecture_milestone_2_queue_whatsapp_web_weeks_4_6_validated_key_refinements", "relation": "contains", "confidence": "EXTRACTED", "source_file": ".planning/research/ARCHITECTURE.md", "source_location": "L360", "weight": 1.0}, {"source": "research_architecture_suggested_build_order_milestone_validation_refinement", "target": "research_architecture_milestone_3_official_channels_fallback_weeks_7_8_validated", "relation": "contains", "confidence": "EXTRACTED", "source_file": ".planning/research/ARCHITECTURE.md", "source_location": "L383", "weight": 1.0}, {"source": "research_architecture_architecture_research", "target": "research_architecture_missing_components_structural_gaps", "relation": "contains", "confidence": "EXTRACTED", "source_file": ".planning/research/ARCHITECTURE.md", "source_location": "L403", "weight": 1.0}, {"source": "research_architecture_missing_components_structural_gaps", "target": "research_architecture_gap_1_publish_side_idempotency_via_nats_msg_id_high_impact_low_effort", "relation": "contains", "confidence": "EXTRACTED", "source_file": ".planning/research/ARCHITECTURE.md", "source_location": "L408", "weight": 1.0}, {"source": "research_architecture_missing_components_structural_gaps", "target": "research_architecture_gap_2_native_per_subject_backpressure_via_maxmsgspersubject_discardnewpersubject_high_impact_low_effort", "relation": "contains", "confidence": "EXTRACTED", "source_file": ".planning/research/ARCHITECTURE.md", "source_location": "L415", "weight": 1.0}, {"source": "research_architecture_missing_components_structural_gaps", "target": "research_architecture_gap_3_no_automatic_dead_letter_for_the_messages_stream_medium_impact_medium_effort", "relation": "contains", "confidence": "EXTRACTED", "source_file": ".planning/research/ARCHITECTURE.md", "source_location": "L423", "weight": 1.0}, {"source": "research_architecture_missing_components_structural_gaps", "target": "research_architecture_gap_4_two_driver_stacks_and_two_migration_systems_medium_impact_low_effort_documentation_structure", "relation": "contains", "confidence": "EXTRACTED", "source_file": ".planning/research/ARCHITECTURE.md", "source_location": "L431", "weight": 1.0}, {"source": "research_architecture_missing_components_structural_gaps", "target": "research_architecture_gap_5_startup_reconnect_storm_protection_high_impact_low_effort", "relation": "contains", "confidence": "EXTRACTED", "source_file": ".planning/research/ARCHITECTURE.md", "source_location": "L441", "weight": 1.0}, {"source": "research_architecture_missing_components_structural_gaps", "target": "research_architecture_gap_6_whatsapp_web_version_auto_refresh_medium_impact_low_effort", "relation": "contains", "confidence": "EXTRACTED", "source_file": ".planning/research/ARCHITECTURE.md", "source_location": "L450", "weight": 1.0}, {"source": "research_architecture_missing_components_structural_gaps", "target": "research_architecture_gap_7_workqueue_single_consumer_topology_must_be_documented_low_impact_documentation", "relation": "contains", "confidence": "EXTRACTED", "source_file": ".planning/research/ARCHITECTURE.md", "source_location": "L457", "weight": 1.0}, {"source": "research_architecture_missing_components_structural_gaps", "target": "research_architecture_gap_8_copyfrom_is_connection_level_not_pool_level_low_impact_implementation_detail", "relation": "contains", "confidence": "EXTRACTED", "source_file": ".planning/research/ARCHITECTURE.md", "source_location": "L464", "weight": 1.0}, {"source": "research_architecture_missing_components_structural_gaps", "target": "research_architecture_gap_9_getdevice_requires_an_ad_jid_low_impact_implementation_detail", "relation": "contains", "confidence": "EXTRACTED", "source_file": ".planning/research/ARCHITECTURE.md", "source_location": "L470", "weight": 1.0}, {"source": "research_architecture_missing_components_structural_gaps", "target": "research_architecture_gap_10_idempotency_at_the_provider_boundary_medium_impact_design_decision", "relation": "contains", "confidence": "EXTRACTED", "source_file": ".planning/research/ARCHITECTURE.md", "source_location": "L476", "weight": 1.0}, {"source": "research_architecture_architecture_research", "target": "research_architecture_scaling_considerations", "relation": "contains", "confidence": "EXTRACTED", "source_file": ".planning/research/ARCHITECTURE.md", "source_location": "L487", "weight": 1.0}, {"source": "research_architecture_scaling_considerations", "target": "research_architecture_scaling_priorities_in_order_of_what_breaks_first", "relation": "contains", "confidence": "EXTRACTED", "source_file": ".planning/research/ARCHITECTURE.md", "source_location": "L495", "weight": 1.0}, {"source": "research_architecture_architecture_research", "target": "research_architecture_anti_patterns_to_avoid", "relation": "contains", "confidence": "EXTRACTED", "source_file": ".planning/research/ARCHITECTURE.md", "source_location": "L509", "weight": 1.0}, {"source": "research_architecture_architecture_research", "target": "research_architecture_integration_points", "relation": "contains", "confidence": "EXTRACTED", "source_file": ".planning/research/ARCHITECTURE.md", "source_location": "L524", "weight": 1.0}, {"source": "research_architecture_integration_points", "target": "research_architecture_external_services", "relation": "contains", "confidence": "EXTRACTED", "source_file": ".planning/research/ARCHITECTURE.md", "source_location": "L526", "weight": 1.0}, {"source": "research_architecture_integration_points", "target": "research_architecture_internal_boundaries", "relation": "contains", "confidence": "EXTRACTED", "source_file": ".planning/research/ARCHITECTURE.md", "source_location": "L537", "weight": 1.0}, {"source": "research_architecture_architecture_research", "target": "research_architecture_sources", "relation": "contains", "confidence": "EXTRACTED", "source_file": ".planning/research/ARCHITECTURE.md", "source_location": "L551", "weight": 1.0}], "input_tokens": 0, "output_tokens": 0}